[
  {
    "netbasalinsulin": 0, 
    "activity": 0.0627, 
    "basaliob": 0, 
    "time": "2016-07-31T17:55:29.000Z", 
    "hightempinsulin": 0, 
    "bolussnooze": 6.047, 
    "iob": 16.525
  }, 
  {
    "netbasalinsulin": 0, 
    "activity": 0.0757, 
    "basaliob": 0, 
    "time": "2016-07-31T18:00:29.000Z", 
    "hightempinsulin": 0, 
    "bolussnooze": 3.446, 
    "iob": 16.147
  }, 
  {
    "netbasalinsulin": 0, 
    "activity": 0.0886, 
    "basaliob": 0, 
    "time": "2016-07-31T18:05:29.000Z", 
    "hightempinsulin": 0, 
    "bolussnooze": 1.583, 
    "iob": 15.704
  }, 
  {
    "netbasalinsulin": 0, 
    "activity": 0.1015, 
    "basaliob": 0, 
    "time": "2016-07-31T18:10:29.000Z", 
    "hightempinsulin": 0, 
    "bolussnooze": 0.459, 
    "iob": 15.197
  }, 
  {
    "netbasalinsulin": 0, 
    "activity": 0.1144, 
    "basaliob": 0, 
    "time": "2016-07-31T18:15:29.000Z", 
    "hightempinsulin": 0, 
    "bolussnooze": 0.029, 
    "iob": 14.624
  }, 
  {
    "netbasalinsulin": 0, 
    "activity": 0.1274, 
    "basaliob": 0, 
    "time": "2016-07-31T18:20:29.000Z", 
    "hightempinsulin": 0, 
    "bolussnooze": 0, 
    "iob": 13.988
  }, 
  {
    "netbasalinsulin": 0, 
    "activity": 0.1403, 
    "basaliob": 0, 
    "time": "2016-07-31T18:25:29.000Z", 
    "hightempinsulin": 0, 
    "bolussnooze": 0, 
    "iob": 13.286
  }, 
  {
    "netbasalinsulin": 0, 
    "activity": 0.1532, 
    "basaliob": 0, 
    "time": "2016-07-31T18:30:29.000Z", 
    "hightempinsulin": 0, 
    "bolussnooze": 0, 
    "iob": 12.52
  }, 
  {
    "netbasalinsulin": 0, 
    "activity": 0.1661, 
    "basaliob": 0, 
    "time": "2016-07-31T18:35:29.000Z", 
    "hightempinsulin": 0, 
    "bolussnooze": 0, 
    "iob": 11.689
  }, 
  {
    "netbasalinsulin": 0, 
    "activity": 0.1791, 
    "basaliob": 0, 
    "time": "2016-07-31T18:40:29.000Z", 
    "hightempinsulin": 0, 
    "bolussnooze": 0, 
    "iob": 10.794
  }, 
  {
    "netbasalinsulin": 0, 
    "activity": 0.1883, 
    "basaliob": 0, 
    "time": "2016-07-31T18:45:29.000Z", 
    "hightempinsulin": 0, 
    "bolussnooze": 0, 
    "iob": 9.848
  }, 
  {
    "netbasalinsulin": 0, 
    "activity": 0.186, 
    "basaliob": 0, 
    "time": "2016-07-31T18:50:29.000Z", 
    "hightempinsulin": 0, 
    "bolussnooze": 0, 
    "iob": 8.909
  }, 
  {
    "netbasalinsulin": 0, 
    "activity": 0.1768, 
    "basaliob": 0, 
    "time": "2016-07-31T18:55:29.000Z", 
    "hightempinsulin": 0, 
    "bolussnooze": 0, 
    "iob": 8.025
  }, 
  {
    "netbasalinsulin": 0, 
    "activity": 0.1676, 
    "basaliob": 0, 
    "time": "2016-07-31T19:00:29.000Z", 
    "hightempinsulin": 0, 
    "bolussnooze": 0, 
    "iob": 7.188
  }, 
  {
    "netbasalinsulin": 0, 
    "activity": 0.1583, 
    "basaliob": 0, 
    "time": "2016-07-31T19:05:29.000Z", 
    "hightempinsulin": 0, 
    "bolussnooze": 0, 
    "iob": 6.396
  }, 
  {
    "netbasalinsulin": 0, 
    "activity": 0.1491, 
    "basaliob": 0, 
    "time": "2016-07-31T19:10:29.000Z", 
    "hightempinsulin": 0, 
    "bolussnooze": 0, 
    "iob": 5.651
  }, 
  {
    "netbasalinsulin": 0, 
    "activity": 0.1399, 
    "basaliob": 0, 
    "time": "2016-07-31T19:15:29.000Z", 
    "hightempinsulin": 0, 
    "bolussnooze": 0, 
    "iob": 4.951
  }, 
  {
    "netbasalinsulin": 0, 
    "activity": 0.1306, 
    "basaliob": 0, 
    "time": "2016-07-31T19:20:29.000Z", 
    "hightempinsulin": 0, 
    "bolussnooze": 0, 
    "iob": 4.298
  }, 
  {
    "netbasalinsulin": 0, 
    "activity": 0.1214, 
    "basaliob": 0, 
    "time": "2016-07-31T19:25:29.000Z", 
    "hightempinsulin": 0, 
    "bolussnooze": 0, 
    "iob": 3.692
  }, 
  {
    "netbasalinsulin": 0, 
    "activity": 0.1122, 
    "basaliob": 0, 
    "time": "2016-07-31T19:30:29.000Z", 
    "hightempinsulin": 0, 
    "bolussnooze": 0, 
    "iob": 3.131
  }, 
  {
    "netbasalinsulin": 0, 
    "activity": 0.1029, 
    "basaliob": 0, 
    "time": "2016-07-31T19:35:29.000Z", 
    "hightempinsulin": 0, 
    "bolussnooze": 0, 
    "iob": 2.616
  }, 
  {
    "netbasalinsulin": 0, 
    "activity": 0.0937, 
    "basaliob": 0, 
    "time": "2016-07-31T19:40:29.000Z", 
    "hightempinsulin": 0, 
    "bolussnooze": 0, 
    "iob": 2.148
  }, 
  {
    "netbasalinsulin": 0, 
    "activity": 0.0845, 
    "basaliob": 0, 
    "time": "2016-07-31T19:45:29.000Z", 
    "hightempinsulin": 0, 
    "bolussnooze": 0, 
    "iob": 1.726
  }, 
  {
    "netbasalinsulin": 0, 
    "activity": 0.0752, 
    "basaliob": 0, 
    "time": "2016-07-31T19:50:29.000Z", 
    "hightempinsulin": 0, 
    "bolussnooze": 0, 
    "iob": 1.35
  }, 
  {
    "netbasalinsulin": 0, 
    "activity": 0.066, 
    "basaliob": 0, 
    "time": "2016-07-31T19:55:29.000Z", 
    "hightempinsulin": 0, 
    "bolussnooze": 0, 
    "iob": 1.02
  }, 
  {
    "netbasalinsulin": 0, 
    "activity": 0.0568, 
    "basaliob": 0, 
    "time": "2016-07-31T20:00:29.000Z", 
    "hightempinsulin": 0, 
    "bolussnooze": 0, 
    "iob": 0.736
  }, 
  {
    "netbasalinsulin": 0, 
    "activity": 0.0475, 
    "basaliob": 0, 
    "time": "2016-07-31T20:05:29.000Z", 
    "hightempinsulin": 0, 
    "bolussnooze": 0, 
    "iob": 0.499
  }, 
  {
    "netbasalinsulin": 0, 
    "activity": 0.0383, 
    "basaliob": 0, 
    "time": "2016-07-31T20:10:29.000Z", 
    "hightempinsulin": 0, 
    "bolussnooze": 0, 
    "iob": 0.307
  }, 
  {
    "netbasalinsulin": 0, 
    "activity": 0.0291, 
    "basaliob": 0, 
    "time": "2016-07-31T20:15:29.000Z", 
    "hightempinsulin": 0, 
    "bolussnooze": 0, 
    "iob": 0.162
  }, 
  {
    "netbasalinsulin": 0, 
    "activity": 0.0198, 
    "basaliob": 0, 
    "time": "2016-07-31T20:20:29.000Z", 
    "hightempinsulin": 0, 
    "bolussnooze": 0, 
    "iob": 0.063
  }, 
  {
    "netbasalinsulin": 0, 
    "activity": 0.0106, 
    "basaliob": 0, 
    "time": "2016-07-31T20:25:29.000Z", 
    "hightempinsulin": 0, 
    "bolussnooze": 0, 
    "iob": 0.01
  }, 
  {
    "netbasalinsulin": 0, 
    "activity": 0.0029, 
    "basaliob": 0, 
    "time": "2016-07-31T20:30:29.000Z", 
    "hightempinsulin": 0, 
    "bolussnooze": 0, 
    "iob": -0.003
  }, 
  {
    "netbasalinsulin": 0, 
    "activity": 0, 
    "basaliob": 0, 
    "time": "2016-07-31T20:35:29.000Z", 
    "hightempinsulin": 0, 
    "bolussnooze": 0, 
    "iob": 0
  }, 
  {
    "netbasalinsulin": 0, 
    "activity": 0, 
    "basaliob": 0, 
    "time": "2016-07-31T20:40:29.000Z", 
    "hightempinsulin": 0, 
    "bolussnooze": 0, 
    "iob": 0
  }, 
  {
    "netbasalinsulin": 0, 
    "activity": 0, 
    "basaliob": 0, 
    "time": "2016-07-31T20:45:29.000Z", 
    "hightempinsulin": 0, 
    "bolussnooze": 0, 
    "iob": 0
  }, 
  {
    "netbasalinsulin": 0, 
    "activity": 0, 
    "basaliob": 0, 
    "time": "2016-07-31T20:50:29.000Z", 
    "hightempinsulin": 0, 
    "bolussnooze": 0, 
    "iob": 0
  }
]